{
  "generator-jhipster": {
    "promptValues": {
      "packageName": "com.dirac.sales",
      "nativeLanguage": "en"
    },
    "jhipsterVersion": "6.3.0",
    "applicationType": "monolith",
    "baseName": "customer",
    "packageName": "com.dirac.sales",
    "packageFolder": "com/dirac/sales",
    "serverPort": "8080",
    "authenticationType": "jwt",
    "cacheProvider": "ehcache",
    "enableHibernateCache": true,
    "websocket": false,
    "databaseType": "sql",
    "devDatabaseType": "h2Disk",
    "prodDatabaseType": "mysql",
    "searchEngine": false,
    "messageBroker": false,
    "serviceDiscoveryType": false,
    "buildTool": "maven",
    "enableSwaggerCodegen": false,
    "jwtSecretKey": "MGFiNTg0MzVmOGYwNDA1Y2Q0NzliZjBkMTMwZmYwNWZjNzkwZTg3YmI2ODI3OGMyOThiOGZiYmY2NTViYzEyMjI2NDAwYTFhMGRiZmViZDJjOTM5YzJhNDU2YjljYTM1ZDdkMDViZjMwYWUyM2IzYTIyZGVkMjNiMGNmZTI4N2Y=",
    "embeddableLaunchScript": false,
    "useSass": true,
    "clientPackageManager": "npm",
    "clientFramework": "angularX",
    "clientTheme": "none",
    "clientThemeVariant": "",
    "testFrameworks": [],
    "jhiPrefix": "jhi",
    "entitySuffix": "",
    "dtoSuffix": "DTO",
    "otherModules": [],
    "enableTranslation": true,
    "nativeLanguage": "en",
    "languages": ["en", "ar-ly"],
    "blueprints": []
  }
}
